{
  "openapi": "3.0.1",
  "info": {
    "title": "MultiSearchAPI",
    "version": "1.0"
  },
  "paths": {
    "/api/Equipments": {
      "get": {
        "tags": [
          "Equipments"
        ],
        "responses": {
          "200": {
            "description": "Success",
            "content": {
              "text/plain": {
                "schema": {
                  "type": "array",
                  "items": {
                    "$ref": "#/components/schemas/Equipment"
                  }
                }
              },
              "application/json": {
                "schema": {
                  "type": "array",
                  "items": {
                    "$ref": "#/components/schemas/Equipment"
                  }
                }
              },
              "text/json": {
                "schema": {
                  "type": "array",
                  "items": {
                    "$ref": "#/components/schemas/Equipment"
                  }
                }
              }
            }
          }
        }
      }
    },
    "/api/Materials": {
      "get": {
        "tags": [
          "Materials"
        ],
        "responses": {
          "200": {
            "description": "Success",
            "content": {
              "text/plain": {
                "schema": {
                  "type": "array",
                  "items": {
                    "$ref": "#/components/schemas/Material"
                  }
                }
              },
              "application/json": {
                "schema": {
                  "type": "array",
                  "items": {
                    "$ref": "#/components/schemas/Material"
                  }
                }
              },
              "text/json": {
                "schema": {
                  "type": "array",
                  "items": {
                    "$ref": "#/components/schemas/Material"
                  }
                }
              }
            }
          }
        }
      }
    },
    "/api/Produtos": {
      "get": {
        "tags": [
          "Produtos"
        ],
        "responses": {
          "200": {
            "description": "Success",
            "content": {
              "text/plain": {
                "schema": {
                  "type": "array",
                  "items": {
                    "$ref": "#/components/schemas/Produto"
                  }
                }
              },
              "application/json": {
                "schema": {
                  "type": "array",
                  "items": {
                    "$ref": "#/components/schemas/Produto"
                  }
                }
              },
              "text/json": {
                "schema": {
                  "type": "array",
                  "items": {
                    "$ref": "#/components/schemas/Produto"
                  }
                }
              }
            }
          }
        }
      }
    },
    "/api/PurchaseOrders": {
      "get": {
        "tags": [
          "PurchaseOrders"
        ],
        "responses": {
          "200": {
            "description": "Success",
            "content": {
              "text/plain": {
                "schema": {
                  "type": "array",
                  "items": {
                    "$ref": "#/components/schemas/PurchaseOrder"
                  }
                }
              },
              "application/json": {
                "schema": {
                  "type": "array",
                  "items": {
                    "$ref": "#/components/schemas/PurchaseOrder"
                  }
                }
              },
              "text/json": {
                "schema": {
                  "type": "array",
                  "items": {
                    "$ref": "#/components/schemas/PurchaseOrder"
                  }
                }
              }
            }
          }
        }
      }
    },
    "/api/SalesOrders": {
      "get": {
        "tags": [
          "SalesOrders"
        ],
        "responses": {
          "200": {
            "description": "Success",
            "content": {
              "text/plain": {
                "schema": {
                  "type": "array",
                  "items": {
                    "$ref": "#/components/schemas/SalesOrder"
                  }
                }
              },
              "application/json": {
                "schema": {
                  "type": "array",
                  "items": {
                    "$ref": "#/components/schemas/SalesOrder"
                  }
                }
              },
              "text/json": {
                "schema": {
                  "type": "array",
                  "items": {
                    "$ref": "#/components/schemas/SalesOrder"
                  }
                }
              }
            }
          }
        }
      }
    },
    "/api/Search": {
      "get": {
        "tags": [
          "Search"
        ],
        "parameters": [
          {
            "name": "query",
            "in": "query",
            "schema": {
              "type": "string"
            }
          }
        ],
        "responses": {
          "200": {
            "description": "Success",
            "content": {
              "text/plain": {
                "schema": {
                  "type": "array",
                  "items": { }
                }
              },
              "application/json": {
                "schema": {
                  "type": "array",
                  "items": { }
                }
              },
              "text/json": {
                "schema": {
                  "type": "array",
                  "items": { }
                }
              }
            }
          }
        }
      }
    },
    "/api/Workforce": {
      "get": {
        "tags": [
          "Workforce"
        ],
        "responses": {
          "200": {
            "description": "Success",
            "content": {
              "text/plain": {
                "schema": {
                  "type": "array",
                  "items": {
                    "$ref": "#/components/schemas/Workforce"
                  }
                }
              },
              "application/json": {
                "schema": {
                  "type": "array",
                  "items": {
                    "$ref": "#/components/schemas/Workforce"
                  }
                }
              },
              "text/json": {
                "schema": {
                  "type": "array",
                  "items": {
                    "$ref": "#/components/schemas/Workforce"
                  }
                }
              }
            }
          }
        }
      }
    }
  },
  "components": {
    "schemas": {
      "Equipment": {
        "type": "object",
        "properties": {
          "equipmentID": {
            "type": "string",
            "nullable": true
          },
          "equipmentName": {
            "type": "string",
            "nullable": true
          }
        },
        "additionalProperties": false
      },
      "Material": {
        "type": "object",
        "properties": {
          "materialID": {
            "type": "string",
            "nullable": true
          },
          "materialName": {
            "type": "string",
            "nullable": true
          }
        },
        "additionalProperties": false
      },
      "Produto": {
        "type": "object",
        "properties": {
          "id": {
            "type": "integer",
            "format": "int32"
          },
          "nome": {
            "type": "string",
            "nullable": true
          },
          "preco": {
            "type": "number",
            "format": "double"
          }
        },
        "additionalProperties": false
      },
      "PurchaseOrder": {
        "type": "object",
        "properties": {
          "purchaseOrderID": {
            "type": "integer",
            "format": "int32"
          },
          "deliveryDate": {
            "type": "string",
            "nullable": true
          },
          "supplier": {
            "type": "string",
            "nullable": true
          },
          "materialID": {
            "type": "string",
            "nullable": true
          },
          "materialName": {
            "type": "string",
            "nullable": true
          },
          "quantity": {
            "type": "integer",
            "format": "int32"
          },
          "totalCost": {
            "type": "number",
            "format": "double"
          }
        },
        "additionalProperties": false
      },
      "SalesOrder": {
        "type": "object",
        "properties": {
          "salesOrderID": {
            "type": "integer",
            "format": "int32"
          },
          "deliveryDate": {
            "type": "string",
            "nullable": true
          },
          "customer": {
            "type": "string",
            "nullable": true
          },
          "materialID": {
            "type": "string",
            "nullable": true
          },
          "materialName": {
            "type": "string",
            "nullable": true
          },
          "quantity": {
            "type": "integer",
            "format": "int32"
          },
          "totalValue": {
            "type": "number",
            "format": "double"
          }
        },
        "additionalProperties": false
      },
      "Workforce": {
        "type": "object",
        "properties": {
          "workforceID": {
            "type": "integer",
            "format": "int32"
          },
          "name": {
            "type": "string",
            "nullable": true
          },
          "shift": {
            "type": "string",
            "nullable": true
          }
        },
        "additionalProperties": false
      }
    }
  }
}